imagecompression8/__init__.py
imagecompression8/compression_algorithm.py
imagecompression8-0.1.12.dist-info/LICENSE.txt
imagecompression8-0.1.12.dist-info/METADATA
imagecompression8-0.1.12.dist-info/WHEEL
imagecompression8-0.1.12.dist-info/top_level.txt
imagecompression8-0.1.12.dist-info/RECORD
